{
  "bills": [
    {
      "id": 1,
      "name": "Fibertel",
      "description": "Internet",
      "date": "1/09/22",
      "amount": 2200,
      "status": "notpaid"
    },
    {
      "id": 2,
      "name": "Edenor",
      "description": "Electricidad",
      "date": "1/09/22",
      "amount": 4000,
      "status": "unknown"
    },
    {
      "id": 3,
      "name": "Movistar",
      "description": "Telefonia movil",
      "date": "1/09/22",
      "amount": 710,
      "status": "unknown"
    },
    {
      "id": 4,
      "name": "Mercado Pago",
      "description": "Credito",
      "date": "1/09/22",
      "amount": 25000,
      "status": "paid"
    },
    {
      "name": "Hominis",
      "description": "Prepaga",
      "date": "1/10/22",
      "amount": 500,
      "status": "notpaid",
      "id": "b07a9481-11fa-4be3-9691-37ac617f5189",
      "createdAt": "11/19/2022, 2:34:02 PM",
      "updatedAt": "11/19/2022, 2:34:03 PM"
    },
    {
      "name": "Tarjeta Naranja",
      "description": "Credito",
      "date": "1/11/22",
      "amount": 13500,
      "status": "notpaid",
      "id": "3bd65096-29e5-4793-877d-97ffc17aec09",
      "createdAt": "11/19/2022, 2:42:33 PM",
      "updatedAt": "11/19/2022, 2:42:33 PM"
    },
    {
      "name": "Alquiler",
      "description": "Vivienda",
      "date": "05/11/22",
      "amount": 46500,
      "status": "paid",
      "id": "5ad61d4f-18b0-40e3-b587-9f568ca8ad92",
      "createdAt": "11/19/2022, 2:45:40 PM",
      "updatedAt": "11/19/2022, 2:45:40 PM"
    },
    {
      "name": "Alquiler",
      "description": "Vivienda",
      "date": "05/10/22",
      "amount": 46500,
      "status": "paid",
      "id": "ead52984-e171-414f-9c67-03acb03c2e4a",
      "createdAt": "11/19/2022, 2:47:58 PM",
      "updatedAt": "11/19/2022, 2:47:58 PM"
    }
  ]
}